Metadata-Version: 1.0
Name: aws-event-parser
Version: 0.3.1
Summary: Small wrapper to aws event and return data
Home-page: https://bitbucket.org
Author: Md Mehrab Alam
Author-email: mdmehrab.alam@delhivery.com
License: UNKNOWN
Platform: UNKNOWN
